snakemake_executor_plugin_azure_batch/__init__.py
snakemake_executor_plugin_azure_batch/build.py
snakemake_executor_plugin_azure_batch/constant.py
snakemake_executor_plugin_azure_batch/util.py
snakemake_executor_plugin_azure_batch-0.3.0.dist-info/LICENSE
snakemake_executor_plugin_azure_batch-0.3.0.dist-info/METADATA
snakemake_executor_plugin_azure_batch-0.3.0.dist-info/WHEEL
snakemake_executor_plugin_azure_batch-0.3.0.dist-info/RECORD
